[
    {
        "codigo": "b1",
        "articulo": "carro rojo",
        "precio": 30.0,
        "stock": 1,
        "categoria": "Jugueteria",
        "imagen": "C:\\Users\\Diana\\OneDrive\\Escritorio\\TIENDA DAYH POOS\\aplicacion\\imagenes_productos\\img_b1.png"
    },
    {
        "codigo": "b2",
        "articulo": "Loteria",
        "precio": 30.0,
        "stock": 1,
        "categoria": "Jugueteria",
        "imagen": "C:\\Users\\Diana\\OneDrive\\Escritorio\\TIENDA DAYH POOS\\aplicacion\\imagenes_productos\\img_b2.png"
    },
    {
        "codigo": "a1",
        "articulo": "sacapunta",
        "precio": 5.0,
        "stock": 2,
        "categoria": "Papeleria",
        "imagen": "C:\\Users\\Diana\\OneDrive\\Escritorio\\TIENDA DAYH POOS\\aplicacion\\imagenes_productos\\img_a1.png"
    },
    {
        "codigo": "a2",
        "articulo": "borrador",
        "precio": 10.0,
        "stock": 4,
        "categoria": "Papeleria",
        "imagen": "C:\\Users\\Diana\\OneDrive\\Escritorio\\TIENDA DAYH POOS\\aplicacion\\imagenes_productos\\img_a2.png"
    },
    {
        "codigo": "c1",
        "articulo": "audifonos",
        "precio": 100.0,
        "stock": 1,
        "categoria": "Electronica",
        "imagen": "C:\\Users\\Diana\\OneDrive\\Escritorio\\TIENDA DAYH POOS\\aplicacion\\imagenes_productos\\img_c1.png"
    },
    {
        "codigo": "c2",
        "articulo": "bocina alexa",
        "precio": 150.0,
        "stock": 1,
        "categoria": "Electronica",
        "imagen": "C:\\Users\\Diana\\OneDrive\\Escritorio\\TIENDA DAYH POOS\\aplicacion\\imagenes_productos\\img_c2.png"
    },
    {
        "codigo": "d1",
        "articulo": "tenis negro",
        "precio": 350.0,
        "stock": 2,
        "categoria": "Calzado",
        "imagen": "C:\\Users\\Diana\\OneDrive\\Escritorio\\TIENDA DAYH POOS\\aplicacion\\imagenes_productos\\img_d1.png"
    },
    {
        "codigo": "d2",
        "articulo": "chancla rosa",
        "precio": 90.0,
        "stock": 1,
        "categoria": "Calzado",
        "imagen": "C:\\Users\\Diana\\OneDrive\\Escritorio\\TIENDA DAYH POOS\\aplicacion\\imagenes_productos\\img_d2.png"
    },
    {
        "codigo": "d3",
        "articulo": "falda gris",
        "precio": 150.0,
        "stock": 1,
        "categoria": "Ropa",
        "imagen": "C:\\Users\\Diana\\OneDrive\\Escritorio\\TIENDA DAYH POOS\\aplicacion\\imagenes_productos\\img_d3.png"
    },
    {
        "codigo": "g1",
        "articulo": "Flores eternas",
        "precio": 350.0,
        "stock": 1,
        "categoria": "manualidades",
        "imagen": "C:\\Users\\Diana\\OneDrive\\Escritorio\\TIENDA DAYH POOS\\aplicacion\\imagenes_productos\\IMG_g1_1781241732.jpeg"
    },
    {
        "codigo": "c3",
        "articulo": "audifonos blanco",
        "precio": 120.0,
        "stock": 1,
        "categoria": "Electronica",
        "imagen": "C:\\Users\\Diana\\OneDrive\\Escritorio\\TIENDA DAYH POOS\\aplicacion\\imagenes_productos\\IMG_c3_1781309704.png"
    }
]